README.md
setup.cfg
setup.py
imdby/__init__.py
imdby/cast_and_crew.py
imdby/company.py
imdby/external_sites.py
imdby/imdb.py
imdby/movie.py
imdby/parental_guide.py
imdby/plot.py
imdby/plot_keywords.py
imdby/release_info.py
imdby/taglines.py
imdby/technical_spec.py
imdby/user_reviews.py
imdby/utils.py
imdby.egg-info/PKG-INFO
imdby.egg-info/SOURCES.txt
imdby.egg-info/dependency_links.txt
imdby.egg-info/requires.txt
imdby.egg-info/top_level.txt