Metadata-Version: 2.1
Name: imdby
Version: 0.0.7
Summary: Python package to access the IMDb's database
Home-page: https://github.com/santhoshse7en/imdby
Author: M Santhosh Kumar
Author-email: santhoshse7en@gmail.com
License: UNKNOWN
Keywords: imdby,imdb,movie,people,database,cinema,film,person,cast,actor,actress,director,sql,character,company,package,plain text data files,keywords,top250,bottom100,xml,bs4
Platform: any
Classifier: Development Status :: 4 - Beta
Classifier: Intended Audience :: End Users/Desktop
Classifier: Intended Audience :: Developers
Classifier: Intended Audience :: System Administrators
Classifier: License :: OSI Approved :: MIT License
Classifier: Operating System :: OS Independent
Classifier: Programming Language :: Python
Classifier: Topic :: Communications :: Email
Classifier: Topic :: Office/Business
Classifier: Topic :: Software Development :: Bug Tracking
Requires-Python: >=3.5
